ryght_image_redaction/__init__.py
ryght_image_redaction/presidio_analyzer/__init__.py
ryght_image_redaction/presidio_analyzer/analysis_explanation.py
ryght_image_redaction/presidio_analyzer/analyzer_engine.py
ryght_image_redaction/presidio_analyzer/analyzer_engine_provider.py
ryght_image_redaction/presidio_analyzer/analyzer_request.py
ryght_image_redaction/presidio_analyzer/analyzer_utils.py
ryght_image_redaction/presidio_analyzer/app_tracer.py
ryght_image_redaction/presidio_analyzer/batch_analyzer_engine.py
ryght_image_redaction/presidio_analyzer/conf/default.yaml
ryght_image_redaction/presidio_analyzer/conf/default_analyzer.yaml
ryght_image_redaction/presidio_analyzer/conf/default_recognizers.yaml
ryght_image_redaction/presidio_analyzer/conf/example_recognizers.yaml
ryght_image_redaction/presidio_analyzer/conf/spacy.yaml
ryght_image_redaction/presidio_analyzer/conf/spacy_multilingual.yaml
ryght_image_redaction/presidio_analyzer/conf/stanza.yaml
ryght_image_redaction/presidio_analyzer/conf/stanza_multilingual.yaml
ryght_image_redaction/presidio_analyzer/conf/transformers.yaml
ryght_image_redaction/presidio_analyzer/context_aware_enhancers/__init__.py
ryght_image_redaction/presidio_analyzer/context_aware_enhancers/context_aware_enhancer.py
ryght_image_redaction/presidio_analyzer/context_aware_enhancers/lemma_context_aware_enhancer.py
ryght_image_redaction/presidio_analyzer/dict_analyzer_result.py
ryght_image_redaction/presidio_analyzer/entity_recognizer.py
ryght_image_redaction/presidio_analyzer/local_recognizer.py
ryght_image_redaction/presidio_analyzer/nlp_engine/__init__.py
ryght_image_redaction/presidio_analyzer/nlp_engine/ner_model_configuration.py
ryght_image_redaction/presidio_analyzer/nlp_engine/nlp_artifacts.py
ryght_image_redaction/presidio_analyzer/nlp_engine/nlp_engine.py
ryght_image_redaction/presidio_analyzer/nlp_engine/nlp_engine_provider.py
ryght_image_redaction/presidio_analyzer/nlp_engine/spacy_nlp_engine.py
ryght_image_redaction-0.1.3.dist-info/LICENSE
ryght_image_redaction-0.1.3.dist-info/METADATA
ryght_image_redaction-0.1.3.dist-info/WHEEL
ryght_image_redaction-0.1.3.dist-info/RECORD
